{
  "cookies": {
    "_GRECAPTCHA": "09ADiQh0dDtO0JP66ailzt3PDzxggDCGN455P-jgR3E6Fa4urUhPJqpbOUwijWhHph2ja48T52OQInEQU0Kpf_K3A",
    "eps_sid": "d2b4ddfcc937b9ad.1762931425.Y6O6T0dXthd5HvD89cZOgvV1DULrMG4pBgtVbTpZ3Z8=",
    "tmpt": "0:3e3f423d2e000000:1762931426408:63ff00b5:f8b3179392320bf36ef02ba725c31f91:7bfb353c17446f42beb57ec93127b3da2665d56b2ea06a9cc16519585e87ca44",
    "SID": "zkWISgPITElwzBzIdByqORqV_MUTorDfhw5euOt8cDwmOR14fu8Q-GbXbnV_Kzx7kSltcDVsxm7Y-Ju6",
    "BID": "CLU_tzYec8DAYCDwLJLAjoQ1TUVXN7gQbi1UdErPye9h60V76bWCFeBpjMP4mNilRVtKF4Y3gKXeCR2R",
    "mt.v": "2.1559226477.1762931427708",
    "mt.pc": "2.1",
    "TMUO": "east_58/NS1LPdKHecYcwKPzxYVJJM9lP9Uy/HOWXmT48PaU=",
    "mt.g.2f013145": "2.1559226477.1762931427708",
    "_ga": "GA1.1.772665721.1762931428",
    "_ga_C1T806G4DF": "GS2.1.s1762931428$o1$g0$t1762931428$j60$l0$h0",
    "_ga_H1KKSGW33X": "GS2.1.s1762931428$o1$g0$t1762931428$j60$l0$h0",
    "TM_PIXEL": "{\"_dvs\":\"0:mhvnus1v:RM9jkarexuRK2nqDxaCDJmo42~NaNl6Q\",\"_dvp\":\"0:mhvnus1v:bDC9Ix1m~kqk5LFoYhaTZnAxQsHJTOeJ\"}",
    "_dvs": "0:mhvnus1v:RM9jkarexuRK2nqDxaCDJmo42~NaNl6Q",
    "_dvp": "0:mhvnus1v:bDC9Ix1m~kqk5LFoYhaTZnAxQsHJTOeJ",
    "_pn": "eyJzdWIiOnsidWRyIjowLCJzcyI6MH0sImx1YSI6MTc2MjkzMTQyODUyNn0",
    "OptanonGroups": ",C0001,",
    "OptanonConsent": "isGpcEnabled=0&datestamp=Wed+Nov+12+2025+02%3A10%3A28+GMT-0500+(Eastern+Standard+Time)&version=202506.1.0&browserGpcFlag=0&isIABGlobal=false&hosts=&consentId=5343c062-e1f9-4f68-af52-178a6386de71&interactionCount=0&isAnonUser=1&landingPath=https%3A%2F%2Fwww.ticketmaster.ca%2Fevent%2F1000631AC8663089&groups=C0001%3A1%2CC0003%3A0%2CC0002%3A0%2CC0004%3A0",
    "__gads": "ID=69afdce40e563d7e:T=1762931429:RT=1762931429:S=ALNI_MbQbSJhFBPG-6CmB4j1yfc0MN-8Aw",
    "__gpi": "UID=000012c7e5454f39:T=1762931429:RT=1762931429:S=ALNI_MY9H1A6lZxQeZOfHvzfQIA_tehdZg",
    "__eoi": "ID=1a223a655c67ddc9:T=1762931429:RT=1762931429:S=AA-AfjZc_PsyI3BnObEf0wePA-L9",
    "IDE": "AHWqTUkNF245eBPv2fHzoZnwSIgyEzz37OgRI2oxAdf3_AbaxkbSPBbo9lcri9pBA-w",
    "LANGUAGE": "en-ca"
  },
  "headers": {
    "sec-ch-ua-platform": "\"macOS\"",
    "referer": "https://www.ticketmaster.ca/",
    "user-agent": "Mozilla/5.0 (Macintosh; Intel Mac OS X 10_15_7) AppleWebKit/537.36 (KHTML, like Gecko) HeadlessChrome/140.0.7339.16 Safari/537.36",
    "tmps-correlation-id": "0d80848a-9376-471a-9ba2-bfb21ea1fb96",
    "sec-ch-ua": "\"Chromium\";v=\"140\", \"Not=A?Brand\";v=\"24\", \"HeadlessChrome\";v=\"140\"",
    "sec-ch-ua-mobile": "?0"
  }
}
